bfchain_pc_sdk
