Metadata-Version: 2.1
Name: bfchain-pc-sdk
Version: 0.0.8
Summary: BFchain SDK for Python
Home-page: https://bfcc.dev/
Author: Jiang Chao
Author-email: jiangchao_mars@163.com
License: UNKNOWN
Platform: UNKNOWN
Classifier: Development Status :: 3 - Alpha
Classifier: Intended Audience :: Developers
Classifier: Topic :: Software Development :: Build Tools
Classifier: Programming Language :: Python :: 2.7
Classifier: Operating System :: OS Independent
Requires-Python: >=2.7, <3
